LICENSE
MANIFEST.in
README.rst
setup.cfg
setup.py
etc/newrelic_marklogic.conf.sample
newrelic_marklogic_plugin/__init__.py
newrelic_marklogic_plugin/http_utils.py
newrelic_marklogic_plugin/marklogic_status.py
newrelic_marklogic_plugin/newrelic_utils.py
newrelic_marklogic_plugin.egg-info/PKG-INFO
newrelic_marklogic_plugin.egg-info/SOURCES.txt
newrelic_marklogic_plugin.egg-info/dependency_links.txt
newrelic_marklogic_plugin.egg-info/requires.txt
newrelic_marklogic_plugin.egg-info/top_level.txt
scripts/newrelic_marklogic.py