Metadata-Version: 1.1
Name: newrelic-marklogic-plugin
Version: 0.2.7
Summary: NewRelic plugin for monitoring MarkLogic.
Home-page: http://github.com/marklogic/newrelic_marklogic
Author: James Fuller
Author-email: jim.fuller@marklogic.com
License:                                  Apache License
